[
  {
    "id": 1,
    "label": "{\"label\":\"Глава администрации федеральной территории «Сириус»\",\"position\":\"Глава администрации\",\"avatarUrl\":null,\"type\":\"department\"}",
    "children": [
      {
        "id": 223,
        "label": "{\"label\":\"Сектор по организации деятельности антитеррористической комиссии федеральной территории «Сириус»\",\"position\":\"Глава администрации федеральной территории «Сириус»\",\"avatarUrl\":\"https://sirius-ft.ru/upload/iblock/0ac/bqsll2y7e5l1zh20uyon8je2lfdblqyy.webp  \",\"type\":\"employee\",\"fullName\":\"Дмитрий Сергеевич Плишкин\",\"phone\":\"+7 (999) 123-45-67\",\"work_phone\":\"101\",\"email\":\"dmitriy.plishkin@example.com\"}",
        "children": []
      },
      {
        "id": 224,
        "label": "{\"label\":\"Сектор по организации деятельности антитеррористической комиссии федеральной территории «Сириус»\",\"position\":\"Помощник главы администрации федеральной территории «Сириус»\",\"avatarUrl\":\"https://sirius-ft.ru/upload/iblock/78c/y18xn3h97bbj02c5mvyo6012f51nzb36.webp  \",\"type\":\"employee\",\"fullName\":\"Артем Сергеевич Столяров\",\"phone\":\"+7 (999) 234-56-78\",\"work_phone\":\"102\",\"email\":\"artem.stolyarov@example.com\"}",
        "children": []
      },
      {
        "id": 2,
        "label": "{\"label\":\"Сектор по организации деятельности антитеррористической комиссии федеральной территории «Сириус»\",\"position\":\"Начальник сектора\",\"avatarUrl\":null,\"type\":\"department\"}",
        "children": []
      },
      {
        "id": 3,
        "label": "{\"label\":\"Сектор по защите государственной тайны и мобилизационной работы\",\"position\":\"Начальник сектора\",\"avatarUrl\":null,\"type\":\"department\"}",
        "children": []
      },
      {
        "id": 4,
        "label": "{\"label\":\"Сектор по профилактике коррупционных и иных правонарушений\",\"position\":\"Начальник сектора\",\"avatarUrl\":null,\"type\":\"department\"}",
        "children": []
      },
      {
        "id": 5,
        "label": "{\"label\":\"Сектор финансового контроля\",\"position\":\"Начальник сектора\",\"avatarUrl\":null,\"type\":\"department\"}",
        "children": []
      },
      {
        "id": 6,
        "label": "{\"label\":\"Помощник главы администрации федеральной территории «Сириус»\",\"position\":\"Помощник главы\",\"avatarUrl\":null,\"type\":\"department\"}",
        "children": []
      },
      {
        "id": 7,
        "label": "{\"label\":\"Руководитель аппарата администрации федеральной территории «Сириус»\",\"position\":\"Руководитель аппарата\",\"avatarUrl\":null,\"type\":\"department\"}",
        "children": [
          {
            "id": 225,
            "label": "{\"label\":\"Сектор по организации деятельности антитеррористической комиссии федеральной территории «Сириус»\",\"position\":\"Руководитель аппарата администрации федеральной территории «Сириус»\",\"avatarUrl\":\"https://sirius-ft.ru/upload/iblock/03c/qsbr52yh07qw5u2xzn029yvsjfa8ckrn.jpg  \",\"type\":\"employee\",\"fullName\":\"Омельченко Наталия Валерьевна\",\"phone\":\"+7 (999) 345-67-89\",\"work_phone\":\"103\",\"email\":\"natalia.omelchenko@example.com\"}",
            "children": []
          },
          {
            "id": 8,
            "label": "{\"label\":\"Аппарат администрации федеральной территории «Сириус»\",\"position\":\"Сотрудник аппарата\",\"avatarUrl\":null,\"type\":\"department\"}",
            "children": []
          },
          {
            "id": 9,
            "label": "{\"label\":\"Правовой департамент администрации федеральной территории «Сириус»\",\"position\":\"Директор департамента\",\"avatarUrl\":null,\"type\":\"department\"}",
            "children": [
              {
                "id": 227,
                "label": "{\"label\":\"Сектор по организации деятельности антитеррористической комиссии федеральной территории «Сириус»\",\"position\":\"Директор департамента\",\"avatarUrl\":null,\"type\":\"employee\",\"fullName\":\"Наталья Владимировна Шаргаева\",\"phone\":\"+7 (999) 456-78-90\",\"work_phone\":\"104\",\"email\":\"natalia.shargaeva@example.com\"}",
                "children": []
              }
            ]
          }
        ]
      },
      {
        "id": 10,
        "label": "{\"label\":\"Заместитель главы администрации федеральной территории «Сириус» – директор департамента экономического развития\",\"position\":\"Заместитель главы\",\"avatarUrl\":null,\"type\":\"department\"}",
        "children": [
          {
            "id": 115,
            "label": "{\"label\":\"Департамент экономического развития\",\"position\":\"Заместитель главы администрации федеральной территории «Сириус» – директор департамента экономического развития\",\"avatarUrl\":\"https://sirius-ft.ru/upload/iblock/c23/aupilqndh2k4343sblqajwkj17neeibt.jpg  \",\"type\":\"employee\",\"fullName\":\"Надежда Сергеевна Казанцева\",\"phone\":\"+7 (999) 567-89-01\",\"work_phone\":\"105\",\"email\":\"nadezhda.kazantseva@example.com\"}",
            "children": []
          },
          {
            "id": 11,
            "label": "{\"label\":\"Департамент экономического развития\",\"position\":\"Директор департамента\",\"avatarUrl\":null,\"type\":\"department\"}",
            "children": []
          },
          {
            "id": 12,
            "label": "{\"label\":\"Департамент финансов\",\"position\":\"Директор департамента\",\"avatarUrl\":null,\"type\":\"department\"}",
            "children": [
              {
                "id": 116,
                "label": "{\"label\":\"Департамент экономического развития\",\"position\":\"Директор департамента\",\"avatarUrl\":\"https://sirius-ft.ru/upload/iblock/789/n5qfzyful6ad6esbj2l4ho81grv5x1l8.jpg  \",\"type\":\"employee\",\"fullName\":\"Верташ Надежда Витальевна\",\"phone\":\"+7 (999) 678-90-12\",\"work_phone\":\"106\",\"email\":\"nadezhda.vertash@example.com\"}",
                "children": []
              }
            ]
          },
          {
            "id": 13,
            "label": "{\"label\":\"Департамент комплексного развития городской среды администрации федеральной территории «Сириус»\",\"position\":\"Директор департамента\",\"avatarUrl\":null,\"type\":\"department\"}",
            "children": [
              {
                "id": 117,
                "label": "{\"label\":\"Департамент комплексного развития городской среды администрации федеральной территории «Сириус»\",\"position\":\"Исполняющий обязанности директора департамента\",\"avatarUrl\":null,\"type\":\"employee\",\"fullName\":\"Митькин Антон Борисович\",\"phone\":\"+7 (999) 789-01-23\",\"work_phone\":\"107\",\"email\":\"anton.mitkin@example.com\"}",
                "children": []
              }
            ]
          }
        ]
      },
      {
        "id": 14,
        "label": "{\"label\":\"Заместитель главы администрации федеральной территории «Сириус» – директор департамента имущественных отношений\",\"position\":\"Заместитель главы\",\"avatarUrl\":null,\"type\":\"department\"}",
        "children": [
          {
            "id": 156,
            "label": "{\"label\":\"Департамент имущественных отношений\",\"position\":\"директор департамента имущественных отношений\",\"avatarUrl\":\"https://sirius-ft.ru/upload/iblock/bb2/2gwpstnj0swug300feenyrp4zfs69yo2.webp  \",\"type\":\"employee\",\"fullName\":\"Сергей Юрьевич Фадеев\",\"phone\":\"+7 (999) 890-12-34\",\"work_phone\":\"108\",\"email\":\"sergey.fadeev@example.com\"}",
            "children": []
          },
          {
            "id": 15,
            "label": "{\"label\":\"Департамент имущественных отношений\",\"position\":\"Директор департамента\",\"avatarUrl\":null,\"type\":\"department\"}",
            "children": []
          },
          {
            "id": 16,
            "label": "{\"label\":\"Департамент архитектуры и градостроительной деятельности\",\"position\":\"Директор департамента\",\"avatarUrl\":null,\"type\":\"department\"}",
            "children": [
              {
                "id": 158,
                "label": "{\"label\":\"Департамент архитектуры и градостроительной деятельности администрации федеральной территории «Сириус»\",\"position\":\"директор департамента\",\"avatarUrl\":\"https://sirius-ft.ru/upload/iblock/f44/326rgfhg57x9m354uxt6ymzfs8x3trbq.webp  \",\"type\":\"employee\",\"fullName\":\"Гинтер Евгения Владимировна\",\"phone\":\"+7 (999) 901-23-45\",\"work_phone\":\"109\",\"email\":\"evgenia.ginter@example.com\"}",
                "children": []
              }
            ]
          }
        ]
      },
      {
        "id": 17,
        "label": "{\"label\":\"Заместитель главы администрации федеральной территории «Сириус» – директор департамента научно-технологического развития, образования, культуры, молодежной политики и спорта\",\"position\":\"Заместитель главы\",\"avatarUrl\":null,\"type\":\"department\"}",
        "children": [
          {
            "id": 159,
            "label": "{\"label\":\"Департамент архитектуры и градостроительной деятельности администрации федеральной территории «Сириус»\",\"position\":\"Заместитель главы администрации федеральной территории «Сириус» – директор департамента научно-технологического развития, образования, культуры, молодежной политики и спорта\",\"avatarUrl\":\"https://sirius-ft.ru/upload/iblock/2d4/cmpmkbg68vn255kwskvw06za8xzry0l1.jpg  \",\"type\":\"employee\",\"fullName\":\"Новокрещенов Илья Владимирович\",\"phone\":\"+7 (999) 012-34-56\",\"work_phone\":\"110\",\"email\":\"ilya.novokreschenov@example.com\"}",
            "children": []
          },
          {
            "id": 18,
            "label": "{\"label\":\"Департамент научно-технологического развития, образования, культуры, молодежной политики и спорта\",\"position\":\"Директор департамента\",\"avatarUrl\":null,\"type\":\"department\"}",
            "children": []
          },
          {
            "id": 19,
            "label": "{\"label\":\"Департамент труда и социального развития администрации федеральной территории «Сириус»\",\"position\":\"Директор департамента\",\"avatarUrl\":null,\"type\":\"department\"}",
            "children": [
              {
                "id": 160,
                "label": "{\"label\":\"Департамент архитектуры и градостроительной деятельности администрации федеральной территории «Сириус»\",\"position\":\"Директор департамента\",\"avatarUrl\":\"https://sirius-ft.ru/upload/iblock/b17/yhnh5tldy2vw2mzl0tgdrk9m0qjelshd.webp  \",\"type\":\"employee\",\"fullName\":\"Наталья Юрьевна Шкалова\",\"phone\":\"+7 (999) 123-45-68\",\"work_phone\":\"111\",\"email\":\"natalia.shkalova@example.com\"}",
                "children": []
              }
            ]
          },
          {
            "id": 20,
            "label": "{\"label\":\"Департамент внутренней политики и организационной деятельности\",\"position\":\"Директор департамента\",\"avatarUrl\":null,\"type\":\"department\"}",
            "children": [
              {
                "id": 161,
                "label": "{\"label\":\"Департамент архитектуры и градостроительной деятельности администрации федеральной территории «Сириус»\",\"position\":\"Исполняющий обязанности директора департамента внутренней политики и организационной деятельности администрации федеральной территории «Сириус»\",\"avatarUrl\":\"https://sirius-ft.ru/upload/iblock/857/2mv9137eiyu3eqgoac1zyih0vh78srs7.jpg  \",\"type\":\"employee\",\"fullName\":\"Михайлов Сергей Евгеньевич\",\"phone\":\"+7 (999) 234-56-79\",\"work_phone\":\"112\",\"email\":\"sergey.mikhailov@example.com\"}",
                "children": []
              }
            ]
          }
        ]
      }
    ]
  }
]